Metadata-Version: 2.1
Name: gretadistributions
Version: 0.1
Summary: Gaussian distributions
